torch_adata/__init__.py
torch_adata/__version__.py
torch_adata/_core/_AnnDataset.py
torch_adata/_core/__init__.py
torch_adata/_core/_core_ancilliary/__init__.py
torch_adata/_core/_core_ancilliary/_data_typing.py
torch_adata/_core/_core_ancilliary/_fetch_data.py
torch_adata/_core/_core_ancilliary/_group_and_pad_adata.py
torch_adata/_core/_core_ancilliary/_identity_msg.py
torch_adata/_core/_core_ancilliary/_one_hot_encode.py
torch_adata/_core/_core_ancilliary/_register_init.py
torch_adata/_core/_core_ancilliary/_return_data_on_axis.py
torch_adata/_core/_lightning/__init__.py
torch_adata/_core/_lightning/_auto_parse_base_class.py
torch_adata/_core/_lightning/_configure_adata.py
torch_adata/_core/_lightning/_function_kwargs.py
torch_adata/_core/_lightning/_lightning_anndata_module.py
torch_adata/_core/_lightning/_train_val_split.py
torch_adata/_demo/__init__.py
torch_adata/_demo/_demo_data.py
torch_adata/_demo/_larry.py
torch_adata/_demo/_pbmc_3k.py
torch_adata/_demo/_plot_umap.py
torch_adata/_tools/__init__.py
torch_adata/_tools/_anndataset_split.py
torch_adata/_tools/_base_lightning_data_module.py
torch_adata/_tools/_dummy_batch.py
torch_adata/_tools/_fetch_data.py
torch_adata/_tools/_idx.py
torch_adata/_tools/_split.py
torch_adata/_utils/__init__.py
torch_adata/_utils/_abc_parse.py
torch_adata/_utils/_function_inspector.py
torch_adata/_utils/_info_message.py
torch_adata-0.1.1.dist-info/LICENSE
torch_adata-0.1.1.dist-info/METADATA
torch_adata-0.1.1.dist-info/WHEEL
torch_adata-0.1.1.dist-info/top_level.txt
torch_adata-0.1.1.dist-info/RECORD
