Metadata-Version: 2.2
Name: torch_adata
Version: 0.1.1
Summary: torch-adata: bridging AnnData-based data models to torch.
Home-page: https://github.com/mvinyard/torch-adata
Author: Michael E. Vinyard
Author-email: mvinyard.ai@gmail.com
License: MIT
Classifier: Development Status :: 2 - Pre-Alpha
Classifier: Programming Language :: Python :: 3.9
Classifier: Intended Audience :: Science/Research
Classifier: Topic :: Scientific/Engineering :: Bio-Informatics
Requires-Python: >3.9.0
License-File: LICENSE
Requires-Dist: anndata>=0.11.3
Requires-Dist: licorice_font>=0.0.3
Requires-Dist: lightning>=2.0.1
Requires-Dist: torch>=2.0
Requires-Dist: scanpy>=1.11.0
Requires-Dist: scikit-learn>=1.2.2
Requires-Dist: webfiles
Requires-Dist: vinplots
Dynamic: author
Dynamic: author-email
Dynamic: classifier
Dynamic: description
Dynamic: description-content-type
Dynamic: home-page
Dynamic: license
Dynamic: requires-dist
Dynamic: requires-python
Dynamic: summary
